Metadata-Version: 2.1
Name: medium-multiply-tutorial
Version: 0.1.0
Summary: Medium Multiply Tutorial library
Home-page: https://medium-multiply.readthedocs.io/
Author: Damon Weiss
Author-email: damonweiss@ethoscollaborative.com
License: MIT
Platform: UNKNOWN
Classifier: Intended Audience :: Developers
Classifier: License :: OSI Approved :: MIT License
Classifier: Programming Language :: Python
Classifier: Programming Language :: Python :: 3.7
Classifier: Programming Language :: Python :: 3.8
Classifier: Programming Language :: Python :: 3.9
Classifier: Operating System :: OS Independent
Requires-Dist: numpy
